[
    {
        "name": "N&L",
        "nameZh": "N&L",
        "location": "G/F, Wah Hing Building, 29 Yan Hing Street, Tai Po Market, Tai Po",
        "metroStation": "Tai Po Market",
        "recommendedTime": "'",
        "avgExpense": "'$101-200",
        "reviewCount": 9.0,
        "reviewScore": 9.0,
        "openTime": "11:00 - 17:00, 17:30 - 22:00"
    },
    {
        "name": "開飯主義",
        "nameZh": "開飯主義",
        "location": "G/F, Block C, Po Wah Building, 1-27 Tai Ming Lane, Tai Po Market, Tai Po",
        "metroStation": "Tai Po Market",
        "recommendedTime": "'",
        "avgExpense": "'$51-100",
        "reviewCount": 203.0,
        "reviewScore": 177.0,
        "openTime": "07:00 - 22:30"
    },
    {
        "name": "金泰泰式美食",
        "nameZh": "金泰泰式美食",
        "location": "Shop CFS39, 2/F, Tai Po Hui Market and Cooked Food Centre, 8 Heung Sze Wui Street, Tai Po",
        "metroStation": "Tai Po Market",
        "recommendedTime": "'",
        "avgExpense": "'$50以下",
        "reviewCount": 61.0,
        "reviewScore": 45.0,
        "openTime": "11:00 - 16:00, 18:00 - 22:00"
    },
    {
        "name": "東記上海麵",
        "nameZh": "東記上海麵",
        "location": "Shop CSF27, 2/F, Tai Po Hui Market and Cooked Food Centre, 8 Heung Sze Wui Street, Tai Po",
        "metroStation": "Tai Po Market",
        "recommendedTime": "'",
        "avgExpense": "'$50以下",
        "reviewCount": 198.0,
        "reviewScore": 142.0,
        "openTime": "07:30 - 16:30"
    },
    {
        "name": "世記上海麵店",
        "nameZh": "世記上海麵店",
        "location": "2/F, Tai Po Hui Market and Cooked Food Centre, 8 Heung Sze Wui Street, Tai Po",
        "metroStation": "Tai Po Market",
        "recommendedTime": "'",
        "avgExpense": "'$50以下",
        "reviewCount": 96.0,
        "reviewScore": 74.0,
        "openTime": "06:00 - 16:00"
    },
    {
        "name": "三小姐海鮮小菜",
        "nameZh": "三小姐海鮮小菜",
        "location": "Shop CFS35, 2/F, Tai Po Hui Market and Cooked Food Centre, 8 Heung Sze Wui Street, Tai Po",
        "metroStation": "Tai Po Market",
        "recommendedTime": "'",
        "avgExpense": "'$101-200",
        "reviewCount": 121.0,
        "reviewScore": 63.0,
        "openTime": "17:00 - 23:00"
    },
    {
        "name": "陳記潮味館",
        "nameZh": "陳記潮味館",
        "location": "Shop D, G/F, Mei Fung Building, 6 Wan Tau Kok Lane, Tai Po Market, Tai Po",
        "metroStation": "Tai Po Market",
        "recommendedTime": "'",
        "avgExpense": "'$51-100",
        "reviewCount": 3.0,
        "reviewScore": 3.0,
        "openTime": "17:00 - 03:00"
    },
    {
        "name": "泰國佬海南雞飯專門店",
        "nameZh": "泰國佬海南雞飯專門店",
        "location": "G/F, 22A Tai Ming Lane, Tai Po Market, Tai Po",
        "metroStation": "Tai Po Market",
        "recommendedTime": "'",
        "avgExpense": "'$51-100",
        "reviewCount": 8.0,
        "reviewScore": 8.0,
        "openTime": "12:00 - 00:00"
    },
    {
        "name": "新樂園大排檔",
        "nameZh": "新樂園大排檔",
        "location": "Shop CFS01, 2/F, Tai Po Hui Market and Cooked Food Centre, 8 Heung Sze Wui Street, Tai Po",
        "metroStation": "Tai Po Market",
        "recommendedTime": "'",
        "avgExpense": "'$101-200",
        "reviewCount": 6.0,
        "reviewScore": 6.0,
        "openTime": "16:00 - 02:00"
    },
    {
        "name": "滑嘟嘟",
        "nameZh": "滑嘟嘟",
        "location": "Shop CFS29, 2/F, Tai Po Hui Market and Cooked Food Centre, 8 Heung Sze Wui Street, Tai Po",
        "metroStation": "Tai Po Market",
        "recommendedTime": "'",
        "avgExpense": "'$50以下",
        "reviewCount": 84.0,
        "reviewScore": 74.0,
        "openTime": "12:00 - 20:00"
    },
    {
        "name": "林記點心",
        "nameZh": "林記點心",
        "location": "Shop CFS08-09, 2/F, Tai Po Hui Market and Cooked Food Centre, 8 Heung Sze Wui Street, Tai Po",
        "metroStation": "Tai Po Market",
        "recommendedTime": "'",
        "avgExpense": "'$50以下",
        "reviewCount": 78.0,
        "reviewScore": 70.0,
        "openTime": {}
    },
    {
        "name": "李記咖啡奶茶",
        "nameZh": "李記咖啡奶茶",
        "location": "Shop CFS33, 2/F, Tai Po Hui Market and Cooked Food Centre, 8 Heung Sze Wui Street, Tai Po",
        "metroStation": "Tai Po Market",
        "recommendedTime": "'",
        "avgExpense": "'$50以下",
        "reviewCount": 28.0,
        "reviewScore": 24.0,
        "openTime": "08:00 - 14:30"
    },
    {
        "name": "伽文晚飯小菜",
        "nameZh": "伽文晚飯小菜",
        "location": "Shop CFS2, 2/F, Tai Po Hui Market and Cooked Food Centre, 8 Heung Sze Wui Street, Tai Po",
        "metroStation": "Tai Po Market",
        "recommendedTime": "'",
        "avgExpense": "'$50以下",
        "reviewCount": 13.0,
        "reviewScore": 9.0,
        "openTime": "11:00 - 15:00, 17:00 - 22:00"
    },
    {
        "name": "英記中泰美食",
        "nameZh": "英記中泰美食",
        "location": "Shop CSF40, 2/F, Tai Po Hui Market and Cooked Food Centre, 8 Heung Sze Wui Street, Tai Po",
        "metroStation": "Tai Po Market",
        "recommendedTime": "'",
        "avgExpense": "'$51-100",
        "reviewCount": 6.0,
        "reviewScore": 4.0,
        "openTime": "全日休息"
    },
    {
        "name": "鴻發牛什魚蛋專家",
        "nameZh": "鴻發牛什魚蛋專家",
        "location": "Shop CFS7, 2/F, Tai Po Hui Market and Cooked Food Centre, 8 Heung Sze Wui Street, Tai Po",
        "metroStation": "Tai Po Market",
        "recommendedTime": "'",
        "avgExpense": "'$50以下",
        "reviewCount": 46.0,
        "reviewScore": 38.0,
        "openTime": "06:00 - 20:00"
    },
    {
        "name": "魚仔魚湯米線",
        "nameZh": "魚仔魚湯米線",
        "location": "Shop CFS19, 2/F, Tai Po Hui Market and Cooked Food Centre, 8 Heung Sze Wui Street, Tai Po",
        "metroStation": "Tai Po Market",
        "recommendedTime": "'",
        "avgExpense": "'$50以下",
        "reviewCount": 7.0,
        "reviewScore": 7.0,
        "openTime": "08:00 - 16:00"
    },
    {
        "name": "文興",
        "nameZh": "文興",
        "location": "Shop CFS13, 2/F, Tai Po Hui Market and Cooked Food Centre, 8 Heung Sze Wui Street, Tai Po",
        "metroStation": "Tai Po Market",
        "recommendedTime": "'",
        "avgExpense": "'$50以下",
        "reviewCount": 10.0,
        "reviewScore": 10.0,
        "openTime": {}
    },
    {
        "name": "有記茶果",
        "nameZh": "有記茶果",
        "location": "2/F, Tai Po Hui Market and Cooked Food Centre, 8 Heung Sze Wui Street, Tai Po",
        "metroStation": "Tai Po Market",
        "recommendedTime": "'",
        "avgExpense": "'$51-100",
        "reviewCount": 45.0,
        "reviewScore": 35.0,
        "openTime": {}
    },
    {
        "name": "余曉記上海包",
        "nameZh": "余曉記上海包",
        "location": "G/F, 26-28E Tai Ming Lane, Tai Po Market, Tai Po",
        "metroStation": "Tai Po Market",
        "recommendedTime": "'",
        "avgExpense": "'$50以下",
        "reviewCount": 25.0,
        "reviewScore": 11.0,
        "openTime": "10:00 - 20:00"
    },
    {
        "name": "伍仔記",
        "nameZh": "伍仔記",
        "location": "Shop CF30, 2/F, Tai Po Hui Market and Cooked Food Centre, 8 Heung Sze Wui Street, Tai Po",
        "metroStation": "Tai Po Market",
        "recommendedTime": "'",
        "avgExpense": "'$51-100",
        "reviewCount": 55.0,
        "reviewScore": 29.0,
        "openTime": "17:30 - 00:00"
    },
    {
        "name": "錦華粥粉麵",
        "nameZh": "錦華粥粉麵",
        "location": "Shop CFS14, 2/F, Tai Po Hui Market and Cooked Food Centre, 8 Heung Sze Wui Street, Tai Po",
        "metroStation": "Tai Po Market",
        "recommendedTime": "'",
        "avgExpense": "'$50以下",
        "reviewCount": 21.0,
        "reviewScore": 15.0,
        "openTime": "06:30 - 16:30"
    },
    {
        "name": "蘇記",
        "nameZh": "蘇記",
        "location": "Shop CFS37, 2/F, Tai Po Hui Market and Cooked Food Centre, 8 Heung Sze Wui Street, Tai Po",
        "metroStation": "Tai Po Market",
        "recommendedTime": "'",
        "avgExpense": "'$50以下",
        "reviewCount": 13.0,
        "reviewScore": 9.0,
        "openTime": {}
    },
    {
        "name": "發記粥麵",
        "nameZh": "發記粥麵",
        "location": "Shop CFS18, 2/F, Tai Po Hui Market and Cooked Food Centre, 8 Heung Sze Wui Street, Tai Po",
        "metroStation": "Tai Po Market",
        "recommendedTime": "'",
        "avgExpense": "'$50以下",
        "reviewCount": 21.0,
        "reviewScore": 11.0,
        "openTime": "07:00 - 16:00"
    },
    {
        "name": "城仔記小廚",
        "nameZh": "城仔記小廚",
        "location": "Shop CSF26, 2/F, Tai Po Hui Market and Cooked Food Centre, 8 Heung Sze Wui Street, Tai Po",
        "metroStation": "Tai Po Market",
        "recommendedTime": "'",
        "avgExpense": "'$50以下",
        "reviewCount": 2.0,
        "reviewScore": 0.0,
        "openTime": "07:00 - 11:00, 14:00 - 16:00"
    },
    {
        "name": "洪記",
        "nameZh": "洪記",
        "location": "Shop CFS4, 2/F, Tai Po Hui Market and Cooked Food Centre, 8 Heung Sze Wui Street, Tai Po",
        "metroStation": "Tai Po Market",
        "recommendedTime": "'",
        "avgExpense": "'$50以下",
        "reviewCount": 28.0,
        "reviewScore": 4.0,
        "openTime": "07:00 - 13:00"
    },
    {
        "name": "欽記粉麵",
        "nameZh": "欽記粉麵",
        "location": "Shop CFS36, 2/F, Tai Po Hui Market and Cooked Food Centre, 8 Heung Sze Wui Street, Tai Po",
        "metroStation": "Tai Po Market",
        "recommendedTime": "'",
        "avgExpense": "'$50以下",
        "reviewCount": 43.0,
        "reviewScore": 27.0,
        "openTime": "07:00 - 21:00"
    },
    {
        "name": "平記麵家",
        "nameZh": "平記麵家",
        "location": "2/F, Tai Po Hui Market and Cooked Food Centre, 8 Heung Sze Wui Street, Tai Po",
        "metroStation": "Tai Po Market",
        "recommendedTime": "'",
        "avgExpense": "'$50以下",
        "reviewCount": 50.0,
        "reviewScore": 32.0,
        "openTime": "全日休息"
    },
    {
        "name": "添仔記",
        "nameZh": "添仔記",
        "location": "Shop CF32, 2/F, Tai Po Hui Market and Cooked Food Centre, 8 Heung Sze Wui Street, Tai Po",
        "metroStation": "Tai Po Market",
        "recommendedTime": "'",
        "avgExpense": "'$50以下",
        "reviewCount": 9.0,
        "reviewScore": 3.0,
        "openTime": {}
    },
    {
        "name": "美心MX (港鐵大埔墟站)",
        "nameZh": "美心MX (港鐵大埔墟站)",
        "location": "Shop TAP 17, Tai Po Market MTR Station, Tai Po",
        "metroStation": "Tai Po Market",
        "recommendedTime": "'",
        "avgExpense": "'$50以下",
        "reviewCount": 1.0,
        "reviewScore": 1.0,
        "openTime": "06:00 - 21:30"
    },
    {
        "name": "銓仔記海鮮晚飯小菜",
        "nameZh": "銓仔記海鮮晚飯小菜",
        "location": "Shop CF34-35, 2/F, Tai Po Hui Market and Cooked Food Centre, 8 Heung Sze Wui Street, Tai Po",
        "metroStation": "Tai Po Market",
        "recommendedTime": "'",
        "avgExpense": "'$101-200",
        "reviewCount": 8.0,
        "reviewScore": 6.0,
        "openTime": "11:00 - 22:00"
    },
    {
        "name": "釗記海鮮小菜",
        "nameZh": "釗記海鮮小菜",
        "location": "Shop CFS24, 2/F, Tai Po Hui Market and Cooked Food Centre, 8 Heung Sze Wui Street, Tai Po",
        "metroStation": "Tai Po Market",
        "recommendedTime": "'",
        "avgExpense": "'$50以下",
        "reviewCount": 45.0,
        "reviewScore": 25.0,
        "openTime": "06:00 - 22:00"
    },
    {
        "name": "食味道小廚",
        "nameZh": "食味道小廚",
        "location": "Shop C17, 2/F, Tai Po Hui Market and Cooked Food Centre, 8 Heung Sze Wui Street, Tai Po",
        "metroStation": "Tai Po Market",
        "recommendedTime": "'",
        "avgExpense": "'$51-100",
        "reviewCount": 11.0,
        "reviewScore": 9.0,
        "openTime": "全日休息"
    },
    {
        "name": "大埔煮廚",
        "nameZh": "大埔煮廚",
        "location": "Shop CFS16, 2/F, Tai Po Hui Market and Cooked Food Centre, 8 Heung Sze Wui Street, Tai Po",
        "metroStation": "Tai Po Market",
        "recommendedTime": "'",
        "avgExpense": "'$50以下",
        "reviewCount": 4.0,
        "reviewScore": 4.0,
        "openTime": "08:30 - 17:00"
    },
    {
        "name": "強記鳳爪",
        "nameZh": "強記鳳爪",
        "location": "Shop SM04, 1/F, Tai Po Hui Market and Cooked Food Centre, 8 Heung Sze Wui Street, Tai Po",
        "metroStation": "Tai Po Market",
        "recommendedTime": "'",
        "avgExpense": "'$50以下",
        "reviewCount": 8.0,
        "reviewScore": 8.0,
        "openTime": "08:00 - 19:00"
    },
    {
        "name": "惠陽茶水檔",
        "nameZh": "惠陽茶水檔",
        "location": "Shop CFS5, 2/F, Tai Po Hui Market and Cooked Food Centre, 8 Heung Sze Wui Street, Tai Po",
        "metroStation": "Tai Po Market",
        "recommendedTime": "'",
        "avgExpense": "'$50以下",
        "reviewCount": 7.0,
        "reviewScore": 3.0,
        "openTime": {}
    },
    {
        "name": "星巴克咖啡",
        "nameZh": "星巴克咖啡",
        "location": "Shop TAP 8, Tai Po Market MTR Station, Tai Po",
        "metroStation": "Tai Po Market",
        "recommendedTime": "'",
        "avgExpense": "'$50以下",
        "reviewCount": 8.0,
        "reviewScore": 6.0,
        "openTime": "06:30 - 21:00"
    },
    {
        "name": "魚尚",
        "nameZh": "魚尚",
        "location": "Shop TAP 12, Tai Po Market MTR Station, Tai Po",
        "metroStation": "Tai Po Market",
        "recommendedTime": "'",
        "avgExpense": "'$50以下",
        "reviewCount": 20.0,
        "reviewScore": 12.0,
        "openTime": "07:30 - 22:00"
    },
    {
        "name": "東海堂",
        "nameZh": "東海堂",
        "location": "Shop TAP 13-14, Tai Po Market MTR Station, Tai Po",
        "metroStation": "Tai Po Market",
        "recommendedTime": "'",
        "avgExpense": "'$50以下",
        "reviewCount": 16.0,
        "reviewScore": 16.0,
        "openTime": "07:00 - 22:00"
    },
    {
        "name": "知味棧咸雞咸鴨專門店",
        "nameZh": "知味棧咸雞咸鴨專門店",
        "location": "Shop SM05, 1/F, Tai Po Hui Market and Cooked Food Centre, 8 Heung Sze Wui Street, Tai Po",
        "metroStation": "Tai Po Market",
        "recommendedTime": "'",
        "avgExpense": "'$51-100",
        "reviewCount": 8.0,
        "reviewScore": 8.0,
        "openTime": "08:00 - 19:00"
    },
    {
        "name": "君蘭餅店",
        "nameZh": "君蘭餅店",
        "location": "Shop TAP 18, Tai Po Market MTR Station, Tai Po",
        "metroStation": "Tai Po Market",
        "recommendedTime": "'",
        "avgExpense": "'$50以下",
        "reviewCount": 3.0,
        "reviewScore": 3.0,
        "openTime": "07:00 - 20:30"
    },
    {
        "name": "張煥記",
        "nameZh": "張煥記",
        "location": "Shop CFS28, 2/F, Tai Po Hui Market and Cooked Food Centre, 8 Heung Sze Wui Street, Tai Po",
        "metroStation": "Tai Po Market",
        "recommendedTime": "'",
        "avgExpense": "'$50以下",
        "reviewCount": 13.0,
        "reviewScore": 11.0,
        "openTime": "07:30 - 15:30"
    },
    {
        "name": "鴻機茶室",
        "nameZh": "鴻機茶室",
        "location": "Shop CFS3, 2/F, Tai Po Hui Market and Cooked Food Centre, 8 Heung Sze Wui Street, Tai Po",
        "metroStation": "Tai Po Market",
        "recommendedTime": "'",
        "avgExpense": "'$50以下",
        "reviewCount": 6.0,
        "reviewScore": 2.0,
        "openTime": {}
    }
]